{"nodes": [{"id": "apps_api_src_app_auth_context_ts", "label": "auth-context.ts", "file_type": "code", "source_file": "apps/api/src/app/auth-context.ts", "source_location": "L1"}, {"id": "auth_context_createanonymousauthcontext", "label": "createAnonymousAuthContext()", "file_type": "code", "source_file": "apps/api/src/app/auth-context.ts", "source_location": "L27"}, {"id": "auth_context_extractrequestauditcontext", "label": "extractRequestAuditContext()", "file_type": "code", "source_file": "apps/api/src/app/auth-context.ts", "source_location": "L42"}], "edges": [{"source": "apps_api_src_app_auth_context_ts", "target": "auth_context_createanonymousauthcontext", "relation": "contains", "confidence": "EXTRACTED", "source_file": "apps/api/src/app/auth-context.ts", "source_location": "L27", "weight": 1.0}, {"source": "apps_api_src_app_auth_context_ts", "target": "auth_context_extractrequestauditcontext", "relation": "contains", "confidence": "EXTRACTED", "source_file": "apps/api/src/app/auth-context.ts", "source_location": "L42", "weight": 1.0}], "raw_calls": [{"caller_nid": "auth_context_extractrequestauditcontext", "callee": "isArray", "source_file": "apps/api/src/app/auth-context.ts", "source_location": "L44"}]}